langchain_egnyte/__init__.py
langchain_egnyte/exceptions.py
langchain_egnyte/retriever.py
langchain_egnyte/utilities.py
egnyte_langchain_connector-0.0.4.dist-info/METADATA
egnyte_langchain_connector-0.0.4.dist-info/WHEEL
egnyte_langchain_connector-0.0.4.dist-info/licenses/LICENSE
egnyte_langchain_connector-0.0.4.dist-info/RECORD
