Metadata-Version: 2.4
Name: egnyte-langchain-connector
Version: 0.0.4
Summary: LangChain retriever integration for Egnyte document search and retrieval
Project-URL: Homepage, https://github.com/egnyte/langchain-egnyte
Project-URL: Documentation, https://github.com/egnyte/langchain-egnyte/blob/main/README.md
Project-URL: Repository, https://github.com/egnyte/langchain-egnyte
Project-URL: Issues, https://github.com/egnyte/langchain-egnyte/issues
Project-URL: Changelog, https://github.com/egnyte/langchain-egnyte/blob/main/CHANGELOG.md
Author-email: Abhishek Shahdeo <ashahdeo@egnyte.com>
License: MIT
License-File: LICENSE
Keywords: ai,documents,egnyte,integration,langchain,retriever,sdk
Classifier: Development Status :: 3 - Alpha
Classifier: Intended Audience :: Developers
Classifier: License :: OSI Approved :: MIT License
Classifier: Operating System :: OS Independent
Classifier: Programming Language :: Python :: 3
Classifier: Programming Language :: Python :: 3.11
Classifier: Programming Language :: Python :: 3.12
Classifier: Programming Language :: Python :: 3.13
Classifier: Topic :: Scientific/Engineering :: Artificial Intelligence
Classifier: Topic :: Software Development :: Libraries :: Python Modules
Requires-Python: >=3.11.0
Requires-Dist: httpx>=0.24.0
Requires-Dist: langchain-core>=0.1.0
Requires-Dist: langchain-tests>=0.3.20
Requires-Dist: langchain>=0.1.0
Requires-Dist: pydantic>=2.0.0
Provides-Extra: all
Requires-Dist: langchain-anthropic>=0.1.0; extra == 'all'
Requires-Dist: langchain-openai>=0.1.0; extra == 'all'
Requires-Dist: mkdocs-material>=9.4.8; extra == 'all'
Requires-Dist: mkdocs>=1.5.3; extra == 'all'
Requires-Dist: openai>=1.6.1; extra == 'all'
Provides-Extra: anthropic
Requires-Dist: langchain-anthropic>=0.1.0; extra == 'anthropic'
Provides-Extra: azure
Requires-Dist: langchain-openai>=0.1.0; extra == 'azure'
Provides-Extra: docs
Requires-Dist: mkdocs-material>=9.4.8; extra == 'docs'
Requires-Dist: mkdocs>=1.5.3; extra == 'docs'
Provides-Extra: openai
Requires-Dist: langchain-openai>=0.1.0; extra == 'openai'
Requires-Dist: openai>=1.6.1; extra == 'openai'
Provides-Extra: test
Requires-Dist: langchain-tests>=0.3.20; extra == 'test'
Requires-Dist: pytest-asyncio>=0.20.0; extra == 'test'
Requires-Dist: pytest-socket>=0.6.0; extra == 'test'
Requires-Dist: pytest>=7.0.0; extra == 'test'
Requires-Dist: python-dotenv>=1.0.0; extra == 'test'
